py_clash_configer/__init__.py
py_clash_configer/__main__.py
py_clash_configer/cli/__init__.py
py_clash_configer/cli/context.py
py_clash_configer/cli/merge.py
py_clash_configer/cli/root.py
py_clash_configer/log.py
py_clash_configer/merge.py
py_clash_configer-0.1.0.dist-info/entry_points.txt
py_clash_configer-0.1.0.dist-info/WHEEL
py_clash_configer-0.1.0.dist-info/METADATA
py_clash_configer-0.1.0.dist-info/RECORD
